zwembad/__init__.py
zwembad/pool.py
zwembad-1.2.2.dist-info/LICENSE
zwembad-1.2.2.dist-info/METADATA
zwembad-1.2.2.dist-info/WHEEL
zwembad-1.2.2.dist-info/top_level.txt
zwembad-1.2.2.dist-info/RECORD
